{"document": "doc-063", "pages": [{"id": "doc-063-p0001", "page": 1, "text": "\n# DOW-UAP-D55, Mission Report, Syria, November 2016 - Page 1\n\nDeclassified by MG Richard A. Harrison\nUSCENTCOM Chief of Staff\nDeclassified on: 20 Ma[redacted] 26\n\n~~SECRET//REL TO USA, NATO~~\n\n# 67.1 P-8A OBSERVES UNIDENTIFIED LOW-FLYING OBJECT 55 NM NORTHWEST OF LATAKIA, SYRIA\n\n18 NOV 2016\n\n***\n\n**BLUF:** While monitoring KCTG activity in the Eastern Mediterranean, P-8A, observed an unidentified low-flying object 55 nm northwest of Latakia from an unknown origin, traveling at approx 500KTS on a southeasterly heading outbound from KCTG, for ~2 minutes.\n\n**Timeline (Z):**\n\n(1) [Redacted] 18/1310Z: P-8 observed a possible missile launch IVO [Redacted] 1.4a from an origin unknown detected via the EO/IR sensor. The possible missile appeared to be in sea skim mode traveling at approximately 500KTS on a southeasterly heading outbound from KCTG. P-8 position was 26NM S of object detection at 16121 FT [Redacted] 1.4a\n\n(2) [Redacted] 18/1312Z: - P-8 lost visual of the object IVO [Redacted] 1.4a approx. 40 NM northwest of Latakia. The missile was observed to pass between (RUS) INGUL ARS and 1x U/I vessel.\n\n**Weather:**\n(U) P-8 aircrew characterized visibility as clear, no range limitations.\n\n***\n\n### FLIGHT PATH\n[Image: Map showing flight path, KCTG, and various Russian vessels: (RUS) UDALOY DD-619, (RUS) KUZNETSOV CV-063 (RUS) CHILIKIN AOR, (RUS) KALININGRADNET AD, (RUS) KIROV CON 099, (RUS) INGUL ARS]\n\n*   (1) 1310Z: [Redacted] 1.4a\n*   (2) ~1312Z: [Redacted] 1.4a\n*   26 NM\n*   US P-8A Location 1310Z: [Redacted] 1.4a\n\n***\n\n[Image: Sensor footage showing \"U/I OBJ\", \"(RUS) INGUL ARS\", and \"U/I VESSEL\"]\n\n**CTG 67.1 Comments:** The mission commander for P-8 characterized the interaction as safe. While this was the first observed occurrence of possible missile activity by P-8 aircraft in the Eastern Mediterranean it is assessed to be standard activity consistent with the assessed activity of the KCTG. Video footage can be found at this link: [Redacted] (b)(6)\n\n~~SECRET//REL TO USA, NATO~~\n\nUSCENTCOM MDR 26-0038 to MDR 26-0046 | Approved for Release to AARO | 03/27/26 000001\n"}], "claims": [], "total_claims": 14}